README.md
ppb_tween.py
setup.py
ppb_tween.egg-info/PKG-INFO
ppb_tween.egg-info/SOURCES.txt
ppb_tween.egg-info/dependency_links.txt
ppb_tween.egg-info/requires.txt
ppb_tween.egg-info/top_level.txt