Metadata-Version: 2.1
Name: ppb-tween
Version: 0.2.0
Summary: A tweening system for PursuedPyBear games.
Home-page: https://github.com/ironfroggy/ppb_tween
Author: Calvin Spealman
Author-email: ironfroggy@gmail.com
License: UNKNOWN
Platform: UNKNOWN
Classifier: Programming Language :: Python :: 3
Classifier: Topic :: Games/Entertainment
Provides-Extra: dev
